ap525_python/__init__.py
ap525_python/ap/AP.py
ap525_python/ap/__init__.py
ap525_python/ap/ap_eum.py
ap525_python/ap/search_ap.py
ap525_python/ap/search_ap_class.py
ap525_python/ap/ap_dll/AudioPrecision.API.dll
ap525_python/ap/ap_dll/AudioPrecision.API2.dll
ap525_python/ap/ap_dll/__init__.py
ap525_python/other_control/DM3058E.py
ap525_python/other_control/__init__.py
ap525_python/other_control/contorl_serial.py
ap525_python-0.1.dist-info/METADATA
ap525_python-0.1.dist-info/WHEEL
ap525_python-0.1.dist-info/top_level.txt
ap525_python-0.1.dist-info/RECORD
