Metadata-Version: 2.1
Name: ap525-python
Version: 0.1
Summary: ap python
Author: hewitt
Author-email: pypi_user@163.com
License: MIT
Requires-Dist: pythonnet
Requires-Dist: pyserial
Requires-Dist: PyVISA
Requires-Dist: pandas
Requires-Dist: psutil
